azure/mgmt/computeschedule/__init__.py
azure/mgmt/computeschedule/_client.py
azure/mgmt/computeschedule/_configuration.py
azure/mgmt/computeschedule/_patch.py
azure/mgmt/computeschedule/_validation.py
azure/mgmt/computeschedule/_version.py
azure/mgmt/computeschedule/py.typed
azure/mgmt/computeschedule/_utils/__init__.py
azure/mgmt/computeschedule/_utils/model_base.py
azure/mgmt/computeschedule/_utils/serialization.py
azure/mgmt/computeschedule/aio/__init__.py
azure/mgmt/computeschedule/aio/_client.py
azure/mgmt/computeschedule/aio/_configuration.py
azure/mgmt/computeschedule/aio/_patch.py
azure/mgmt/computeschedule/aio/operations/__init__.py
azure/mgmt/computeschedule/aio/operations/_operations.py
azure/mgmt/computeschedule/aio/operations/_patch.py
azure/mgmt/computeschedule/models/__init__.py
azure/mgmt/computeschedule/models/_enums.py
azure/mgmt/computeschedule/models/_models.py
azure/mgmt/computeschedule/models/_patch.py
azure/mgmt/computeschedule/operations/__init__.py
azure/mgmt/computeschedule/operations/_operations.py
azure/mgmt/computeschedule/operations/_patch.py
azure_mgmt_computeschedule-1.1.0.dist-info/LICENSE
azure_mgmt_computeschedule-1.1.0.dist-info/METADATA
azure_mgmt_computeschedule-1.1.0.dist-info/WHEEL
azure_mgmt_computeschedule-1.1.0.dist-info/top_level.txt
azure_mgmt_computeschedule-1.1.0.dist-info/RECORD
